mailprobe/__init__.py
mailprobe/api.py
mailprobe/cli.py
mailprobe/config.py
mailprobe/database.py
mailprobe/filter.py
mailprobe/message.py
mailprobe/multi_category.py
mailprobe/tokenizer.py
mailprobe/utils.py
mailprobe_py-0.1.0.dist-info/LICENSE
mailprobe_py-0.1.0.dist-info/METADATA
mailprobe_py-0.1.0.dist-info/WHEEL
mailprobe_py-0.1.0.dist-info/entry_points.txt
mailprobe_py-0.1.0.dist-info/RECORD
