Metadata-Version: 2.3
Name: mailprobe-py
Version: 0.1.0
Summary: A Python implementation of advanced Bayesian email classification and filtering
License: MIT
Keywords: email,filter,bayesian,classification,spam,multi-category
Author: Peter Bowen
Author-email: peter-mailprobe@bowenfamily.org
Maintainer: Peter Bowen
Maintainer-email: peter-mailprobe@bowenfamily.org
Requires-Python: >=3.9,<4.0
Classifier: Development Status :: 4 - Beta
Classifier: Intended Audience :: Developers
Classifier: Intended Audience :: System Administrators
Classifier: License :: OSI Approved :: MIT License
Classifier: Operating System :: OS Independent
Classifier: Programming Language :: Python :: 3
Classifier: Programming Language :: Python :: 3.9
Classifier: Programming Language :: Python :: 3.10
Classifier: Programming Language :: Python :: 3.11
Classifier: Programming Language :: Python :: 3.12
Classifier: Programming Language :: Python :: 3.13
Classifier: Topic :: Communications :: Email :: Filters
Classifier: Topic :: Scientific/Engineering :: Artificial Intelligence
Classifier: Topic :: Software Development :: Libraries :: Python Modules
Classifier: Topic :: Text Processing :: Filters
Requires-Dist: click (>=8.0.0,<9.0.0)
Project-URL: Bug Tracker, https://github.com/huntsberg/mailprobe-py/issues
Project-URL: Changelog, https://github.com/huntsberg/mailprobe-py/blob/main/CHANGELOG.md
Project-URL: Documentation, https://github.com/huntsberg/mailprobe-py/blob/main/README.md
Project-URL: Homepage, https://github.com/huntsberg/mailprobe-py
Project-URL: Repository, https://github.com/huntsberg/mailprobe-py
